fyzz/__init__.py
fyzz/ast.py
fyzz/yappsparser/__init__.py
fyzz/yappsparser/parser.py
fyzz-0.2.3.dist-info/METADATA
fyzz-0.2.3.dist-info/WHEEL
fyzz-0.2.3.dist-info/top_level.txt
fyzz-0.2.3.dist-info/RECORD
