Metadata-Version: 2.1
Name: fyzz
Version: 0.2.3
Summary: SPARQL parser
Home-page: https://forge.extranet.logilab.fr/cubicweb/fyzz
Author: Logilab
Author-email: contact@logilab.fr
License: LGPL v2
Platform: UNKNOWN
Requires-Python: >=3.4
Requires-Dist: logilab-common (>=1.6.0)
Requires-Dist: yapps2-logilab (>=2.2.0)
Requires-Dist: setuptools
